__init__.py
myrootmain.py
haha/__init__.py
haha/myhaha.py
haha/myhaha2.py
dswzhytestpip-0.0.2.dist-info/METADATA
dswzhytestpip-0.0.2.dist-info/WHEEL
dswzhytestpip-0.0.2.dist-info/licenses/LICENSE
dswzhytestpip-0.0.2.dist-info/RECORD
