Metadata-Version: 2.1
Name: dswzhytestpip
Version: 0.0.2
Summary: juans is a package for fast iterating your deep learning experiment, it has some helpful tricks which are often used in competition and work by me, and more tricks are on the way!
Project-URL: Homepage, https://github.com/NickYi1990/juans
Author-email: 易灿 <972775099@qq.com>
License: MIT License
License-File: LICENSE
Classifier: License :: OSI Approved :: MIT License
Classifier: Operating System :: OS Independent
Classifier: Programming Language :: Python :: 3
Requires-Python: >=3.7
Requires-Dist: matplotlib>=3.5.1
Requires-Dist: numpy>=1.21.6
